Metadata-Version: 2.1
Name: pyhtmlreport
Version: 1.1
Summary: Implement html reporting in Test Automation
Home-page: https://github.com/michaelsatish/pyhtmlreport
Author: Satish Kumar Kadarkarai Mani
Author-email: michael.satish@gmail.com
License: Apache License 2.0
Keywords: html report
Platform: UNKNOWN
Classifier: Development Status :: 5 - Production/Stable
Classifier: Intended Audience :: Developers
Classifier: Operating System :: POSIX
Classifier: Operating System :: Microsoft :: Windows
Classifier: Operating System :: MacOS :: MacOS X
Classifier: Topic :: Software Development :: Quality Assurance
Classifier: Topic :: Software Development :: Testing
Classifier: Topic :: Utilities
Classifier: Programming Language :: Python :: 3.7
